{
  "_buildCommand2" : {
    "command" : "prepareForIndexing",
    "enableIndexBuildArena" : false,
    "targets" : null
  },
  "buildCommand" : "build",
  "configuredTargets" : [
    {
      "guid" : "bbea4c086f46100b9b2dcbf1297cbff9b3282e4574f186479f68736eb1080ff7"
    }
  ],
  "containerPath" : "/Users/k21116kk/src/imageProc/imgProc_ensyu/第８回/otsu/otsu.xcodeproj",
  "continueBuildingAfterErrors" : true,
  "enableIndexBuildArena" : false,
  "hideShellScriptEnvironment" : false,
  "parameters" : {
    "action" : "build",
    "activeArchitecture" : "arm64",
    "activeRunDestination" : {
      "disableOnlyActiveArch" : false,
      "platform" : "macosx",
      "sdk" : "macosx12.3",
      "sdkVariant" : "macos",
      "supportedArchitectures" : [
        "arm64e",
        "arm64",
        "x86_64"
      ],
      "targetArchitecture" : "arm64"
    },
    "arenaInfo" : {
      "buildIntermediatesPath" : "",
      "buildProductsPath" : "",
      "derivedDataPath" : "/Users/k21116kk/Library/Developer/Xcode/DerivedData",
      "indexDataStoreFolderPath" : "/Users/k21116kk/Library/Developer/Xcode/DerivedData/otsu-btalukzsupnqezhiiygeiedupvbb/Index/DataStore",
      "indexEnableDataStore" : true,
      "indexPCHPath" : "/Users/k21116kk/Library/Developer/Xcode/DerivedData/otsu-btalukzsupnqezhiiygeiedupvbb/Index/PrecompiledHeaders",
      "pchPath" : ""
    },
    "configurationName" : "Debug",
    "overrides" : {
      "synthesized" : {
        "table" : {
          "ENABLE_PREVIEWS" : "NO"
        }
      }
    }
  },
  "qos" : "default",
  "schemeCommand" : "launch",
  "schemeCommand2" : "launch",
  "shouldCollectMetrics" : false,
  "showNonLoggedProgress" : true,
  "useDryRun" : true,
  "useImplicitDependencies" : true,
  "useLegacyBuildLocations" : false,
  "useParallelTargets" : true
}